redundanet/__init__.py
redundanet/__main__.py
redundanet/auth/__init__.py
redundanet/auth/gpg.py
redundanet/auth/keyserver.py
redundanet/cli/__init__.py
redundanet/cli/main.py
redundanet/cli/network.py
redundanet/cli/node.py
redundanet/cli/storage.py
redundanet/core/__init__.py
redundanet/core/config.py
redundanet/core/exceptions.py
redundanet/core/manifest.py
redundanet/core/node.py
redundanet/network/__init__.py
redundanet/network/discovery.py
redundanet/network/dns.py
redundanet/network/validation.py
redundanet/storage/__init__.py
redundanet/storage/client.py
redundanet/storage/furl.py
redundanet/storage/introducer.py
redundanet/storage/storage.py
redundanet/utils/__init__.py
redundanet/utils/files.py
redundanet/utils/logging.py
redundanet/utils/process.py
redundanet/vpn/__init__.py
redundanet/vpn/keys.py
redundanet/vpn/mesh.py
redundanet/vpn/tinc.py
redundanet-2.0.2.dist-info/LICENSE
redundanet-2.0.2.dist-info/METADATA
redundanet-2.0.2.dist-info/WHEEL
redundanet-2.0.2.dist-info/entry_points.txt
redundanet-2.0.2.dist-info/RECORD
