Metadata-Version: 2.1
Name: redundanet
Version: 2.0.2
Summary: Distributed encrypted storage on a mesh VPN network
Home-page: https://github.com/alessandrodefilippo/redundanet
License: MIT
Keywords: distributed-storage,vpn,encryption,mesh-network,tahoe-lafs
Author: Alessandro De Filippo
Author-email: alessandro@example.com
Requires-Python: >=3.11,<4.0
Classifier: Development Status :: 4 - Beta
Classifier: Environment :: Console
Classifier: Intended Audience :: Developers
Classifier: Intended Audience :: System Administrators
Classifier: License :: OSI Approved :: MIT License
Classifier: Operating System :: POSIX :: Linux
Classifier: Programming Language :: Python :: 3
Classifier: Programming Language :: Python :: 3.11
Classifier: Programming Language :: Python :: 3.12
Classifier: Topic :: Security :: Cryptography
Classifier: Topic :: System :: Distributed Computing
Classifier: Topic :: System :: Networking
Requires-Dist: gitpython (>=3.1,<4.0)
Requires-Dist: httpx (>=0.26,<0.27)
Requires-Dist: jinja2 (>=3.1,<4.0)
Requires-Dist: jsonschema (>=4.21,<5.0)
Requires-Dist: psutil (>=5.9,<6.0)
Requires-Dist: pydantic (>=2.5,<3.0)
Requires-Dist: pydantic-settings (>=2.1,<3.0)
Requires-Dist: python-gnupg (>=0.5,<0.6)
Requires-Dist: pyyaml (>=6.0,<7.0)
Requires-Dist: rich (>=13.7,<14.0)
Requires-Dist: structlog (>=24.1,<25.0)
Requires-Dist: typer[all] (>=0.12.0)
Requires-Dist: watchdog (>=4.0,<5.0)
Project-URL: Documentation, https://redundanet.readthedocs.io
Project-URL: Repository, https://github.com/alessandrodefilippo/redundanet
